codecache/__init__.py
codecache/analyzer.py
codecache/cache_manager.py
codecache/cli.py
codecache/config.py
codecache/exceptions.py
codecache/prompt_generator.py
codecache/summarizer.py
codecache-0.1.1.dist-info/LICENSE
codecache-0.1.1.dist-info/METADATA
codecache-0.1.1.dist-info/WHEEL
codecache-0.1.1.dist-info/entry_points.txt
codecache-0.1.1.dist-info/top_level.txt
codecache-0.1.1.dist-info/RECORD
