Metadata-Version: 2.1
Name: codecache
Version: 0.1.1
Summary: Provide LLMs with codebase context for improved coding assistance.
Home-page: https://github.com/dineshrai/codecache
Author: Dinesh Rai
Author-email: drai89@gmail.com
Project-URL: Bug Reports, https://github.com/dineshrai/codecache/issues
Project-URL: Source, https://github.com/dineshrai/codecache
Keywords: codebase analysis,gemini api,context caching,code summarization,cli tool,LLM,coding assistance
Classifier: Development Status :: 3 - Alpha
Classifier: Intended Audience :: Developers
Classifier: Topic :: Software Development :: Code Generators
Classifier: Topic :: Software Development :: Libraries :: Python Modules
Classifier: Environment :: Console
Classifier: Natural Language :: English
Classifier: Programming Language :: Python :: 3
Classifier: Programming Language :: Python :: 3.7
Classifier: License :: OSI Approved :: MIT License
Classifier: Operating System :: OS Independent
Requires-Python: >=3.7
License-File: LICENSE
Requires-Dist: google-generativeai >=0.3.1
Requires-Dist: click >=8.1.3
Requires-Dist: python-dotenv
Requires-Dist: toml
Provides-Extra: dev
Requires-Dist: pytest ; extra == 'dev'
Requires-Dist: pytest-cov ; extra == 'dev'
